{"dependencies":[{"name":"/Users/vvade/Codes/poke/parce/.postcssrc","includedInParent":true,"mtime":1517305322000},{"name":"_css_loader"}],"generated":{"css":"* {\n  -webkit-box-sizing: border-box;\n          box-sizing: border-box;\n  margin: 0;\n  padding: 0;\n}\n\nbody {\n  background: #eeeeee;\n}\n\n._app_sonqv_11 {\n  background: red;\n  height: 56px;\n  min-height: 1px;\n  -webkit-transition: -webkit-transform .3ms ease-in-out;\n  transition: -webkit-transform .3ms ease-in-out;\n  transition: transform .3ms ease-in-out;\n  transition: transform .3ms ease-in-out, -webkit-transform .3ms ease-in-out;\n  display: -webkit-box;\n  display: -ms-flexbox;\n  display: flex;\n}\n","js":"\n        var reloadCSS = require('_css_loader');\n        module.hot.dispose(reloadCSS);\n        module.hot.accept(reloadCSS);\n      module.exports = {\n  \"app\": \"_app_sonqv_11\"\n};"},"hash":"e24d4c17722616b5cd9bb31d14b0d9a6","cacheData":{}}